{
 "actions": [],
 "allow_rename": 1,
 "creation": "2025-09-23 13:49:50.966289",
 "doctype": "DocType",
 "editable_grid": 1,
 "engine": "InnoDB",
 "field_order": [
  "item",
  "price"
 ],
 "fields": [
  {
   "fieldname": "item",
   "fieldtype": "Link",
   "label": "Item",
   "options": "Airplane Ticket Add-on Type"
  },
  {
   "fieldname": "price",
   "fieldtype": "Currency",
   "label": "Price"
  }
 ],
 "grid_page_length": 50,
 "index_web_pages_for_search": 1,
 "istable": 1,
 "links": [],
 "modified": "2025-09-23 13:54:48.096141",
 "modified_by": "Administrator",
 "module": "Airplane Mode",
 "name": "Airplane Ticket Add-on Item",
 "owner": "Administrator",
 "permissions": [],
 "row_format": "Dynamic",
 "sort_field": "modified",
 "sort_order": "DESC",
 "states": []
}